[
  {
    "name": "YUIOP60HH",
    "author": "MURAOKA Taro (a.k.a. KoRoN/KaoriYa)",
    "notes": "HHKB compatible layout "
  },
  [
    {
      "a": 7
    },
    "",
    "",
    "",
    "",
    "",
    "",
    "",
    "",
    "",
    "",
    "",
    "",
    "",
    "",
    ""
  ],
  [
    {
      "w": 1.5
    },
    "",
    "",
    "",
    "",
    "",
    "",
    "",
    "",
    "",
    "",
    "",
    "",
    "",
    {
      "w": 1.5
    },
    ""
  ],
  [
    {
      "w": 1.75
    },
    "",
    "",
    "",
    "",
    "",
    "",
    "",
    "",
    "",
    "",
    "",
    "",
    {
      "w": 2.25
    },
    ""
  ],
  [
    {
      "w": 2.25
    },
    "",
    "",
    "",
    "",
    "",
    "",
    "",
    "",
    "",
    "",
    "",
    {
      "w": 1.75
    },
    "",
    ""
  ],
  [
    {
      "x": 1.5
    },
    "",
    {
      "w": 1.5
    },
    "",
    {
      "w": 6
    },
    "",
    {
      "w": 1.5
    },
    "",
    ""
  ]
]